N/HPSocket4C.dll
N/N.dll
N/N.py
N/__init__.py
N/libeay32.dll
AndroidN-0.0.9.dist-info/METADATA
AndroidN-0.0.9.dist-info/WHEEL
AndroidN-0.0.9.dist-info/top_level.txt
AndroidN-0.0.9.dist-info/RECORD
