Metadata-Version: 2.1
Name: AndroidN
Version: 0.0.9
Summary: Android
Home-page: https://github.com/grayrail000/AndroidQ.git
Author: 1a
Author-email: grayrail1x3@gmail.com
Classifier: Programming Language :: Python :: 3
Classifier: License :: OSI Approved :: MIT License
Classifier: Operating System :: OS Independent
